tkn/__init__.py
tkn/main.py
tkn-0.1.2.dist-info/METADATA
tkn-0.1.2.dist-info/WHEEL
tkn-0.1.2.dist-info/entry_points.txt
tkn-0.1.2.dist-info/RECORD
