Metadata-Version: 2.1
Name: tkn
Version: 0.1.2
Summary: A command-line utility for working with BPE tokenizers
License: MIT
Author: Grayson Chao
Author-email: grayson.chao@gmail.com
Requires-Python: >=3.10,<3.13
Classifier: License :: OSI Approved :: MIT License
Classifier: Programming Language :: Python :: 3
Classifier: Programming Language :: Python :: 3.10
Classifier: Programming Language :: Python :: 3.11
Requires-Dist: tiktoken (>=0.5.1,<0.6.0)
